simple_calc/__init__.py
simple_calc/__main__.py
simple_calc-1.0.7.dist-info/LICENSE
simple_calc-1.0.7.dist-info/METADATA
simple_calc-1.0.7.dist-info/WHEEL
simple_calc-1.0.7.dist-info/entry_points.txt
simple_calc-1.0.7.dist-info/top_level.txt
simple_calc-1.0.7.dist-info/RECORD
